admin_scripts/__init__.py
admin_scripts/base/__init__.py
admin_scripts/base/cleanup.py
admin_scripts/base/encoding.py
admin_scripts/base/join.py
admin_scripts/base/jssource.py
admin_scripts/base/misc.py
admin_scripts/base/pydev.py
admin_scripts/base/pysource.py
admin_scripts/base/stylesheets.py
admin_scripts/base/trailing_spaces.py
admin_scripts/config/__init__.py
admin_scripts/config/development/__init__.py
admin_scripts/config/development/encoding.py
admin_scripts/config/development/join.py
admin_scripts/config/development/jssource.py
admin_scripts/config/development/misc.py
admin_scripts/config/development/pydev.py
admin_scripts/config/development/pysource.py
admin_scripts/config/development/stylesheets.py
admin_scripts/config/development/trailing_spaces.py
admin_scripts/config/extra/jshint.json
admin_scripts/extra/__init__.py
admin_scripts/extra/css.py
admin_scripts/extra/js.py
admin_scripts/extra/lib.py
admin_scripts/extra/log.py
admin_scripts/extra/shell.py
admin_scripts/test/__init__.py
admin_scripts/test/css.py
admin_scripts/test/stylesheets.py
admin_scripts-0.7.0.dist-info/METADATA
admin_scripts-0.7.0.dist-info/WHEEL
admin_scripts-0.7.0.dist-info/entry_points.txt
admin_scripts-0.7.0.dist-info/top_level.txt
admin_scripts-0.7.0.dist-info/RECORD
